topsis/__init__.py
topsis/__main__.py
topsis_arryuann_102103062-1.0.2.dist-info/LICENSE
topsis_arryuann_102103062-1.0.2.dist-info/METADATA
topsis_arryuann_102103062-1.0.2.dist-info/WHEEL
topsis_arryuann_102103062-1.0.2.dist-info/entry_points.txt
topsis_arryuann_102103062-1.0.2.dist-info/top_level.txt
topsis_arryuann_102103062-1.0.2.dist-info/RECORD
