Metadata-Version: 2.1
Name: topsis-arryuann-102103062
Version: 1.0.2
Summary: It returns the csv file with topsis score as well as the rank to the provided csv file.
Home-page: https://github.com/ArryuannKhanna/topsis-arryuann-102103062
Author: Arryuann Khanna
Author-email: aryankhannachd@gmail.com
License: MIT
Classifier: License :: OSI Approved :: MIT License
Classifier: Programming Language :: Python :: 3.6
Classifier: Programming Language :: Python :: 3.7
Classifier: Programming Language :: Python :: 3.8
License-File: LICENSE
Requires-Dist: pandas
Requires-Dist: numpy
